{
  "atom": "logos.vitality.animate",
  "cognitive_mode": "covenant-life",
  "description": "Hebrew-substrate anchor lens. Pivots English 'life' onto \u05d7\u05b7\u05d9\u05bc\u05b4\u05d9\u05dd's logos.vitality.animate atom via the he cognition pack. Cognitive mode: covenant-life. Pair: grc_zoe_v1. See ADR-0073c.",
  "lens_id": "he_chayyim_v1",
  "mastery_report_sha256": "9e7129e37221203625e7a72a07dd8f9048c06314e8f24c7394491bed7de9e9c6",
  "pair_lens_id": "grc_zoe_v1",
  "ratification_method": "anchor_lens_lifts_proposition",
  "schema_version": "1.0.0",
  "source_entry_id": "he-core-cog-004",
  "substrate": "he",
  "version": "1.0.0"
}
