{
  "evidence": {
    "depth_preference": "standard",
    "discourse_markers_empty": false,
    "marker_bucket_sizes": {
      "closings": 3,
      "openings": 4,
      "transitions": 0
    },
    "realizer_overrides_empty": true,
    "realizer_overrides_keys": [],
    "transitions_reserved": false
  },
  "failure_reasons": [],
  "issued_at": "2026-05-20T00:00:00Z",
  "pack_source_sha256": "cf1f477066e3390f152feedb6af113ce0e59ee75a1dc4872a3f2daba73a0c597",
  "ratification_method": "seeded_variation_replay_equivalence",
  "ratified": true,
  "register_id": "contemporary_v1",
  "report_sha256": "3efada036f2dbed1df2bf730f007ad744bd83cc82e13afd5fc3fa83016739c4a",
  "schema_version": "1.0.0"
}
