{
  "register_id": "dry_v1",
  "version": "1.0.0",
  "description": "Dry register — understated, factual.",
  "schema_version": "1.0.0",
  "mastery_report_sha256": "6f413313c0cc42bae47dfb3f1273d429006c0b4405a48764ad6aac8d69da3ebc",
  "display_name": "Dry",
  "depth_preference": "standard",
  "realizer_overrides": {
    "disclosure_domain_count": 2,
    "drop_provenance_tag": true
  },
  "discourse_markers": {
    "openings": [
      "",
      "Stated: ",
      "Plainly — "
    ],
    "transitions": [],
    "closings": [
      "",
      " — that's it."
    ]
  }
}
